{
  "id": 42,
  "idx": 0,
  "news_title": "Annual Gala 2026 - Save the Date",
  "news_excerpt": "Join us for our annual fundraising gala on October 15, 2026, celebrating the arts and community impact.",
  "newscontent": "<p>We're excited to announce our Annual Gala 2026, taking place on October 15th at the Grand Ballroom in Manhattan.</p>\n\n<p>This year's gala will celebrate 15 years of bringing the arts to communities across New York City and beyond. Join us for an evening of music, art, and inspiration as we honor our donors, artists, and community partners who make our mission possible.</p>\n\n<p>Tickets will be available starting in August. Stay tuned for more details!</p>",
  "news_content": {
    "content": "content"
  },
  "news_image": null,
  "news_image_caption": null,
  "news_url": "annual-gala-2026-save-the-date",
  "news_author": "Newsletter Manager Bot",
  "news_date": "2026-02-04 14:30:00.000+00",
  "created_at": "2026-02-04 14:30:15.123456+00",
  "news_updated": null,
  "draft": true,
  "news_status": "draft",
  "featured": false,
  "featured_order": null,
  "news_categories": [
    "events",
    "fundraising"
  ],
  "related_program": null,
  "sun": null
}